setup.py
digPostingDateExtractor/__init__.py
digPostingDateExtractor/date_manipulation.py
digPostingDateExtractor/posting_date_extractor.py
digPostingDateExtractor.egg-info/PKG-INFO
digPostingDateExtractor.egg-info/SOURCES.txt
digPostingDateExtractor.egg-info/dependency_links.txt
digPostingDateExtractor.egg-info/requires.txt
digPostingDateExtractor.egg-info/top_level.txt
test/__init__.py
test/test_posting_date_extractor.py