Metadata-Version: 1.1
Name: digPostingDateExtractor
Version: 0.3.0
Summary: digPostingDateExtractor
Home-page: https://github.com/usc-isi-i2/dig-posting-date-extractor
Author: Lingzhe Teng
Author-email: zwein27@gmail.com
License: UNKNOWN
Download-URL: https://github.com/usc-isi-i2/dig-posting-date-extractor
Keywords: posting,date,extractor
Platform: UNKNOWN
